{"datasets": {"esif": {"columns": ["inwardCode", "projectTitle", "organisationName", "summary", "funds", "euInvestment", "projectCost", "myEuId"], "data": [["1TP", "Cynnydd", "Pembrokeshire County Council", "Providing a full range of engagement, learning and training activities for 11\u201319 year olds in order to reduce the number of young people who are at risk of becoming NEET (Not in Employment, Education or Training).", "ESF", 13333118.0, 19047312.0, "esf_wales_80833"], ["1TP", "Cam Nesa", "Pembrokeshire County Council", "Providing a full range of engagement, learning and training activities for 16 \u2013 24 year olds in order to reduce Youth Unemployment and also reduce the number of young people who are NEET (Not in Employment, Education or Training). Also to increase the attainment levels of 16 \u2013 24 year olds who are NEET.", "ESF", 4000000.0, 5714285.0, "esf_wales_80834"]]}}, "outwardCode": "SA61"}